polyleven.pypy310-pp73-x86_64-linux-gnu.so
polyleven-0.9.0.dist-info/RECORD
polyleven-0.9.0.dist-info/top_level.txt
polyleven-0.9.0.dist-info/LICENSE
polyleven-0.9.0.dist-info/METADATA
polyleven-0.9.0.dist-info/WHEEL
