Metadata-Version: 2.2
Name: polyleven
Version: 0.9.0
Summary: A fast C-implemented library for Levenshtein distance
Maintainer-email: Fujimoto Seiji <fujimoto@ceptord.net>
Project-URL: github, https://github.com/fujimotos/polyleven
Keywords: Levenshtein distance
Classifier: Development Status :: 5 - Production/Stable
Classifier: Operating System :: OS Independent
Classifier: Programming Language :: Python :: 3
Classifier: Programming Language :: C
Requires-Python: >=3.8
License-File: LICENSE
